[{"id": 1, "entry": 1, "exit": 2, "active": false}, 
{"id": 2, "entry": 1, "exit": 3, "active": false}, 
{"id": 3, "entry": 2, "exit": 1, "active": false}, 
{"id": 4, "entry": 2, "exit": 3, "active": false}, 
{"id": 5, "entry": 2, "exit": 5, "active": false}, 
{"id": 6, "entry": 3, "exit": 1, "active": false}, 
{"id": 7, "entry": 3, "exit": 2, "active": false}, 
{"id": 8, "entry": 3, "exit": 5, "active": false}, 
{"id": 9, "entry": 3, "exit": 6, "active": false}, 
{"id": 10, "entry": 4, "exit": 5, "active": true}, 
{"id": 11, "entry": 5, "exit": 3, "active": false}, 
{"id": 12, "entry": 5, "exit": 4, "active": true}, 
{"id": 13, "entry": 5, "exit": 6, "active": true}, 
{"id": 14, "entry": 5, "exit": 7, "active": true}, 
{"id": 15, "entry": 5, "exit": 8, "active": true}, 
{"id": 16, "entry": 5, "exit": 9, "active": true}, 
{"id": 17, "entry": 5, "exit": 10, "active": false}, 
{"id": 18, "entry": 5, "exit": 11, "active": true}, 
{"id": 19, "entry": 6, "exit": 3, "active": false}, 
{"id": 20, "entry": 6, "exit": 5, "active": true}, 
{"id": 21, "entry": 7, "exit": 5, "active": true}, 
{"id": 22, "entry": 7, "exit": 9, "active": true}, 
{"id": 23, "entry": 8, "exit": 5, "active": true}, 
{"id": 24, "entry": 8, "exit": 11, "active": true}, 
{"id": 25, "entry": 9, "exit": 5, "active": true}, 
{"id": 26, "entry": 9, "exit": 7, "active": true}, 
{"id": 27, "entry": 9, "exit": 10, "active": false}, 
{"id": 28, "entry": 10, "exit": 9, "active": false}, 
{"id": 29, "entry": 10, "exit": 11, "active": false}, 
{"id": 30, "entry": 11, "exit": 5, "active": true}, 
{"id": 31, "entry": 11, "exit": 8, "active": true}, 
{"id": 32, "entry": 11, "exit": 10, "active": false}
]